openwisp_users/__init__.py
openwisp_users/admin.py
openwisp_users/apps.py
openwisp_users/backends.py
openwisp_users/middleware.py
openwisp_users/mixins.py
openwisp_users/models.py
openwisp_users/multitenancy.py
openwisp_users/password_validation.py
openwisp_users/settings.py
openwisp_users/tasks.py
openwisp_users/utils.py
openwisp_users/views.py
openwisp_users/widgets.py
openwisp_users/accounts/__init__.py
openwisp_users/accounts/adapter.py
openwisp_users/accounts/urls.py
openwisp_users/accounts/views.py
openwisp_users/accounts/locale/de/LC_MESSAGES/django.po
openwisp_users/accounts/locale/fur/LC_MESSAGES/django.po
openwisp_users/accounts/locale/it/LC_MESSAGES/django.po
openwisp_users/accounts/locale/ru/LC_MESSAGES/django.po
openwisp_users/accounts/locale/sl/LC_MESSAGES/django.po
openwisp_users/accounts/static/openwisp-users/accounts/css/change-password.css
openwisp_users/accounts/static/openwisp-users/accounts/css/non-admin.css
openwisp_users/accounts/templates/account/email_confirm.html
openwisp_users/accounts/templates/account/email_verification_success.html
openwisp_users/accounts/templates/account/login.html
openwisp_users/accounts/templates/account/logout_success.html
openwisp_users/accounts/templates/account/password_change.html
openwisp_users/accounts/templates/account/password_change_success.html
openwisp_users/accounts/templates/account/password_not_required.html
openwisp_users/accounts/templates/account/email/base_message.txt
openwisp_users/accounts/templates/account/email/email_confirmation_message.html
openwisp_users/accounts/templates/account/email/email_confirmation_message.txt
openwisp_users/accounts/templates/account/email/email_confirmation_signup_message.html
openwisp_users/accounts/templates/account/email/password_expiration_message.html
openwisp_users/accounts/templates/account/email/password_expiration_message.txt
openwisp_users/accounts/templates/allauth/layouts/base.html
openwisp_users/api/__init__.py
openwisp_users/api/authentication.py
openwisp_users-1.2.0.dist-info/licenses/LICENSE
openwisp_users-1.2.0.dist-info/METADATA
openwisp_users-1.2.0.dist-info/WHEEL
openwisp_users-1.2.0.dist-info/top_level.txt
openwisp_users-1.2.0.dist-info/RECORD
