Metadata-Version: 2.4
Name: openwisp-users
Version: 1.2.0
Summary: Provides basic multi-tenancy features for OpenWISP (using the Django web-framework)
Home-page: http://openwisp.org
Download-URL: https://github.com/openwisp/openwisp-users/releases
Author: OpenWISP
Author-email: support@openwisp.io
License: BSD
Keywords: openwisp,django,organizations,users
Platform: Platform Independent
Classifier: Development Status :: 5 - Production/Stable
Classifier: Environment :: Web Environment
Classifier: Topic :: Internet :: WWW/HTTP
Classifier: Intended Audience :: Developers
Classifier: License :: OSI Approved :: BSD License
Classifier: Operating System :: OS Independent
Classifier: Framework :: Django
Classifier: Programming Language :: Python :: 3
License-File: LICENSE
Requires-Dist: django-organizations<2.6.0,>=2.5.0
Requires-Dist: django-extensions<4.2,>=3.2
Requires-Dist: django-allauth[socialaccount]<65.13.0,>=65.12.0
Requires-Dist: django-phonenumber-field<8.2.0,>=8.1.0
Requires-Dist: phonenumbers<9.1.0,>=9.0.10
Requires-Dist: openwisp-utils[celery,rest]~=1.2.0
Requires-Dist: packaging
Requires-Dist: django-sesame<3.3.0,>=3.2.3
Dynamic: author
Dynamic: author-email
Dynamic: classifier
Dynamic: description
Dynamic: download-url
Dynamic: home-page
Dynamic: keywords
Dynamic: license
Dynamic: license-file
Dynamic: platform
Dynamic: requires-dist
Dynamic: summary
